{"nodes":[{"label":"Fernando Henrique Cardoso","x":-365.4338684082031,"y":-1022.1212158203125,"id":"5","attributes":{"post_activity":"0.01","fan_count":"521707","link":"https://www.facebook.com/presidentefhc/","talking_about_count":"537","users_can_post":"no","category":"Public Figure","username":"presidentefhc"},"color":"rgb(71,255,249)","size":44.333335876464844},{"label":"Cristiane Brasil","x":398.7911376953125,"y":27.521743774414062,"id":"24","attributes":{"post_activity":"0.08","fan_count":"19635","link":"https://www.facebook.com/cristiane.brasil/","talking_about_count":"465","users_can_post":"no","category":"Politician","username":"cristiane.brasil"},"color":"rgb(71,255,249)","size":11.0},{"label":"Sindvansrio","x":6.680774211883545,"y":-596.3894653320312,"id":"26","attributes":{"post_activity":"0.0","fan_count":"295","link":"https://www.facebook.com/Sindvasrio/","talking_about_count":"2","users_can_post":"yes","category":"Cause","username":"Sindvasrio"},"color":"rgb(71,255,249)","size":11.0},{"label":"Prefeitura do Rio de Janeiro","x":479.280029296875,"y":457.1545715332031,"id":"43","attributes":{"post_activity":"0.09","fan_count":"181377","link":"https://www.facebook.com/PrefeituradoRio/","talking_about_count":"20654","users_can_post":"no","category":"Government Organization","username":"PrefeituradoRio"},"color":"rgb(71,255,249)","size":88.77777862548828},{"label":"PSDB","x":-514.9623413085938,"y":-1083.7596435546875,"id":"9","attributes":{"post_activity":"0.19","fan_count":"1341486","link":"https://www.facebook.com/Rede45/","talking_about_count":"51861","users_can_post":"no","category":"Political Party","username":"Rede45"},"color":"rgb(71,255,249)","size":44.333335876464844},{"label":"Governo do Estado do Rio de Janeiro","x":-313.1127624511719,"y":516.776611328125,"id":"42","attributes":{"post_activity":"0.15","fan_count":"416247","link":"https://www.facebook.com/governodorio/","talking_about_count":"6851","users_can_post":"no","category":"Government Organization","username":"governodorio"},"color":"rgb(71,255,249)","size":44.333335876464844},{"label":"Cidade Olímpica","x":490.05609130859375,"y":810.9581298828125,"id":"44","attributes":{"post_activity":"0.1","fan_count":"277487","link":"https://www.facebook.com/CidadeOlimpica/","talking_about_count":"4053","users_can_post":"no","category":"Government Organization","username":"CidadeOlimpica"},"color":"rgb(71,255,249)","size":111.0},{"label":"Metrô do Rio","x":-711.4215087890625,"y":82.59168243408203,"id":"13","attributes":{"post_activity":"0.04","fan_count":"1344","link":"https://www.facebook.com/Metrô-do-Rio-190147381027883/","talking_about_count":"146","users_can_post":"yes","category":"Community"},"color":"rgb(71,255,249)","size":11.0},{"label":"MulheRio","x":-313.67889404296875,"y":-519.2865600585938,"id":"2","attributes":{"post_activity":"0.01","fan_count":"1616","link":"https://www.facebook.com/movimentomulherio/","talking_about_count":"3","users_can_post":"no","category":"Community","username":"movimentomulherio"},"color":"rgb(71,255,249)","size":11.0},{"label":"Marcelo Ribeiro","x":-90.63624572753906,"y":-439.0149230957031,"id":"39","attributes":{"post_activity":"0.02","fan_count":"6571","link":"https://www.facebook.com/marcelo.ribeiro2735/","talking_about_count":"204","users_can_post":"yes","category":"Public Figure","username":"marcelo.ribeiro2735"},"color":"rgb(71,255,249)","size":11.0},{"label":"PSDB/RJ","x":-506.5497131347656,"y":-307.7111511230469,"id":"8","attributes":{"post_activity":"0.0","fan_count":"329","link":"https://www.facebook.com/pages/PSDBRJ/210458182316223","talking_about_count":"0","users_can_post":"no","category":"Local Business"},"color":"rgb(71,255,249)","size":11.0},{"label":"Empresa Olímpica Municipal","x":219.47543334960938,"y":526.5899047851562,"id":"30","attributes":{"post_activity":"0.05","fan_count":"3542","link":"https://www.facebook.com/empresaolimpica/","talking_about_count":"404","users_can_post":"no","category":"Company","username":"empresaolimpica"},"color":"rgb(71,255,249)","size":22.11111068725586},{"label":"METRÔ QUE O RIO PRECISA","x":-753.5971069335938,"y":-120.96224975585938,"id":"12","attributes":{"post_activity":"0.01","fan_count":"7818","link":"https://www.facebook.com/metroqueorioprecisa/","talking_about_count":"84","users_can_post":"no","category":"Cause","username":"metroqueorioprecisa"},"color":"rgb(71,255,249)","size":22.11111068725586},{"label":"Parque Madureira","x":85.6374282836914,"y":946.4715576171875,"id":"40","attributes":{"post_activity":"0.38","fan_count":"133969","link":"https://www.facebook.com/ParquedeMadureira/","talking_about_count":"6396","users_can_post":"yes","category":"Tours/Sightseeing","username":"ParquedeMadureira"},"color":"rgb(71,255,249)","size":33.22222137451172},{"label":"Secretaria Municipal de Transportes - SMTR","x":937.4814453125,"y":247.50704956054688,"id":"11","attributes":{"post_activity":"0.09","fan_count":"3312","link":"https://www.facebook.com/mobilidaderj/","talking_about_count":"883","users_can_post":"yes","category":"Government Organization","username":"mobilidaderj"},"color":"rgb(71,255,249)","size":33.22222137451172},{"label":"Rioluz Oficial","x":470.6078796386719,"y":-80.49878692626953,"id":"20","attributes":{"post_activity":"0.0","fan_count":"1085","link":"https://www.facebook.com/Rioluz-Oficial-196256910443701/","talking_about_count":"9","users_can_post":"no","category":"Company"},"color":"rgb(71,255,249)","size":22.11111068725586},{"label":"Sávio Neves","x":710.1085815429688,"y":308.9622802734375,"id":"22","attributes":{"post_activity":"0.02","fan_count":"2808","link":"https://www.facebook.com/SavioNevesRJ/","talking_about_count":"158","users_can_post":"no","category":"Business Person","username":"SavioNevesRJ"},"color":"rgb(71,255,249)","size":11.0},{"label":"Bike Anjo","x":517.880126953125,"y":16.620187759399414,"id":"19","attributes":{"post_activity":"0.04","fan_count":"55144","link":"https://www.facebook.com/bikeanjo/","talking_about_count":"334","users_can_post":"no","category":"Community","username":"bikeanjo"},"color":"rgb(71,255,249)","size":22.11111068725586},{"label":"O Globo","x":-110.76164245605469,"y":998.1334228515625,"id":"31","attributes":{"post_activity":"2.59","fan_count":"4855572","link":"https://www.facebook.com/jornaloglobo/","talking_about_count":"512450","users_can_post":"no","category":"News/Media Website","username":"jornaloglobo"},"color":"rgb(71,255,249)","size":88.77777862548828},{"label":"Comlurb - Companhia Municipal de Limpeza Urbana da Cidade do Rio de Janeiro","x":291.4085998535156,"y":223.5054931640625,"id":"29","attributes":{"post_activity":"0.06","fan_count":"7212","link":"https://www.facebook.com/Comlurb/","talking_about_count":"813","users_can_post":"yes","category":"Government Organization","username":"Comlurb"},"color":"rgb(71,255,249)","size":33.22222137451172},{"label":"Juventude PSDB Rio","x":245.46446228027344,"y":-442.3609619140625,"id":"4","attributes":{"post_activity":"0.04","fan_count":"1316","link":"https://www.facebook.com/JuventudePSDBRio/","talking_about_count":"349","users_can_post":"yes","category":"Political Party","username":"JuventudePSDBRio"},"color":"rgb(71,255,249)","size":11.0},{"label":"André do Táxi","x":183.217041015625,"y":-580.2489013671875,"id":"28","attributes":{"post_activity":"0.06","fan_count":"4411","link":"https://www.facebook.com/andretaxirj/","talking_about_count":"1100","users_can_post":"no","category":"Public Figure","username":"andretaxirj"},"color":"rgb(71,255,249)","size":11.0},{"label":"Ingrid Merenda","x":-208.20132446289062,"y":-557.1690673828125,"id":"35","attributes":{"post_activity":"0.01","fan_count":"459","link":"https://www.facebook.com/Ingrid-Merenda-1424964427789145/","talking_about_count":"3","users_can_post":"yes","category":"Public Figure"},"color":"rgb(71,255,249)","size":11.0},{"label":"Metrô Rio","x":-465.15045166015625,"y":197.9098663330078,"id":"10","attributes":{"post_activity":"0.35","fan_count":"172334","link":"https://www.facebook.com/metrodorio/","talking_about_count":"943","users_can_post":"yes","category":"Company","username":"metrodorio"},"color":"rgb(71,255,249)","size":22.11111068725586},{"label":"Jornal O Globo","x":-412.1896057128906,"y":-463.04315185546875,"id":"16","attributes":{"post_activity":"0.0","fan_count":"8034","link":"https://www.facebook.com/pages/Jornal-O-Globo/136193843120820","talking_about_count":"0","users_can_post":"no","category":"Local Business"},"color":"rgb(71,255,249)","size":11.0},{"label":"Ancelmo Gois","x":-336.58160400390625,"y":972.4782104492188,"id":"21","attributes":{"post_activity":"0.27","fan_count":"62434","link":"https://www.facebook.com/AncelmoGoisOGlobo/","talking_about_count":"4880","users_can_post":"no","category":"Journalist","username":"AncelmoGoisOGlobo"},"color":"rgb(71,255,249)","size":22.11111068725586},{"label":"Coordenadoria Especial da Diversidade Sexual/CEDS-RIO","x":326.2757263183594,"y":954.7417602539062,"id":"33","attributes":{"post_activity":"0.1","fan_count":"24213","link":"https://www.facebook.com/CEDSRIO/","talking_about_count":"876","users_can_post":"no","category":"Government Organization","username":"CEDSRIO"},"color":"rgb(71,255,249)","size":33.22222137451172},{"label":"Fabinho Fernandes","x":-294.94610595703125,"y":-361.23309326171875,"id":"36","attributes":{"post_activity":"0.05","fan_count":"6273","link":"https://www.facebook.com/fabinhofernandesrj/","talking_about_count":"1061","users_can_post":"yes","category":"Public Figure","username":"fabinhofernandesrj"},"color":"rgb(71,255,249)","size":11.0},{"label":"PSDBRJ","x":-276.6233215332031,"y":-1104.37451171875,"id":"7","attributes":{"post_activity":"0.13","fan_count":"19035","link":"https://www.facebook.com/PSDBRJ/","talking_about_count":"689","users_can_post":"no","category":"Political Party","username":"PSDBRJ"},"color":"rgb(71,255,249)","size":11.0},{"label":"RIO EU AMO EU CUIDO","x":86.09266662597656,"y":285.35211181640625,"id":"37","attributes":{"post_activity":"0.03","fan_count":"86357","link":"https://www.facebook.com/rioeuamoeucuido/","talking_about_count":"485","users_can_post":"yes","category":"Cause","username":"rioeuamoeucuido"},"color":"rgb(71,255,249)","size":44.333335876464844},{"label":"PSDB Mulher RJ 45","x":-479.8069763183594,"y":-797.9398193359375,"id":"3","attributes":{"post_activity":"0.0","fan_count":"207","link":"https://www.facebook.com/PSDB-Mulher-RJ-45-633481080081544/","talking_about_count":"3","users_can_post":"yes","category":"Political Party"},"color":"rgb(71,255,249)","size":11.0},{"label":"SuperVia","x":-342.0561828613281,"y":819.1866455078125,"id":"15","attributes":{"post_activity":"0.04","fan_count":"51928","link":"https://www.facebook.com/SuperViaRJ/","talking_about_count":"2273","users_can_post":"no","category":"Cargo \u0026 Freight Company","username":"SuperViaRJ"},"color":"rgb(71,255,249)","size":22.11111068725586},{"label":"Carlos Osorio","x":-73.58567810058594,"y":-112.55069732666016,"id":"0","attributes":{"post_activity":"0.29","fan_count":"62102","link":"https://www.facebook.com/osoriorj/","talking_about_count":"3294","users_can_post":"yes","category":"Public Figure","username":"osoriorj"},"color":"rgb(71,255,249)","size":44.333335876464844},{"label":"Jornal O Fluminense","x":-494.3185119628906,"y":594.2129516601562,"id":"17","attributes":{"post_activity":"0.45","fan_count":"256336","link":"https://www.facebook.com/ofluminense/","talking_about_count":"19022","users_can_post":"yes","category":"Media/News/Publishing","username":"ofluminense"},"color":"rgb(71,255,249)","size":11.0},{"label":"Juventude PSDB","x":-413.2222900390625,"y":-1183.7330322265625,"id":"6","attributes":{"post_activity":"0.09","fan_count":"34012","link":"https://www.facebook.com/jpsdb/","talking_about_count":"368","users_can_post":"yes","category":"Political Organization","username":"jpsdb"},"color":"rgb(71,255,249)","size":33.22222137451172},{"label":"BRT Rio","x":734.847900390625,"y":668.09521484375,"id":"32","attributes":{"post_activity":"0.56","fan_count":"206770","link":"https://www.facebook.com/BRTRioOficial/","talking_about_count":"3108","users_can_post":"yes","category":"Cargo \u0026 Freight Company","username":"BRTRioOficial"},"color":"rgb(71,255,249)","size":33.22222137451172},{"label":"Rio 2016","x":149.90817260742188,"y":754.0519409179688,"id":"34","attributes":{"post_activity":"0.32","fan_count":"1645984","link":"https://www.facebook.com/rio2016pt/","talking_about_count":"77956","users_can_post":"no","category":"Sports Event","username":"rio2016pt"},"color":"rgb(71,255,249)","size":99.8888931274414},{"label":"Luiz Fernando Pezão","x":-573.9987182617188,"y":312.0125427246094,"id":"41","attributes":{"post_activity":"0.01","fan_count":"220795","link":"https://www.facebook.com/LFPezao/","talking_about_count":"495","users_can_post":"no","category":"Politician","username":"LFPezao"},"color":"rgb(71,255,249)","size":44.333335876464844},{"label":"Jornal VOZ DA COMUNIDADE","x":-196.3002471923828,"y":688.5598754882812,"id":"14","attributes":{"post_activity":"0.46","fan_count":"62145","link":"https://www.facebook.com/vozdascomunidades/","talking_about_count":"6460","users_can_post":"yes","category":"News/Media Website","username":"vozdascomunidades"},"color":"rgb(71,255,249)","size":44.333335876464844},{"label":"Rio Ônibus","x":916.782470703125,"y":439.2368469238281,"id":"23","attributes":{"post_activity":"0.08","fan_count":"128260","link":"https://www.facebook.com/rioonibus/","talking_about_count":"9662","users_can_post":"no","category":"Cargo \u0026 Freight Company","username":"rioonibus"},"color":"rgb(71,255,249)","size":55.4444465637207},{"label":"Tucanafro - Rio de Janeiro","x":-492.5032653808594,"y":-401.7038879394531,"id":"1","attributes":{"post_activity":"0.01","fan_count":"832","link":"https://www.facebook.com/tucanafrorj/","talking_about_count":"7","users_can_post":"yes","category":"Community","username":"tucanafrorj"},"color":"rgb(71,255,249)","size":11.0},{"label":"Roberto Canazio","x":239.06149291992188,"y":-698.1031494140625,"id":"25","attributes":{"post_activity":"0.01","fan_count":"2719","link":"https://www.facebook.com/Roberto-Canazio-301143503353757/","talking_about_count":"1","users_can_post":"yes","category":"Entertainer"},"color":"rgb(71,255,249)","size":22.11111068725586},{"label":"Felipe Michel","x":-100.41458892822266,"y":-592.1300659179688,"id":"18","attributes":{"post_activity":"0.14","fan_count":"27521","link":"https://www.facebook.com/felipemichelrj/","talking_about_count":"820","users_can_post":"yes","category":"Public Figure","username":"felipemichelrj"},"color":"rgb(71,255,249)","size":11.0},{"label":"Roger Noronha","x":-520.1376953125,"y":-38.55387496948242,"id":"27","attributes":{"post_activity":"0.0","fan_count":"4588","link":"https://www.facebook.com/roger.noronha/","talking_about_count":"6","users_can_post":"yes","category":"Public Figure","username":"roger.noronha"},"color":"rgb(71,255,249)","size":11.0},{"label":"Acme","x":78.18695831298828,"y":-496.75482177734375,"id":"38","attributes":{"post_activity":"0.01","fan_count":"4889","link":"https://www.facebook.com/UniversoAcme/","talking_about_count":"115","users_can_post":"yes","category":"Artist","username":"UniversoAcme"},"color":"rgb(71,255,249)","size":11.0}],"edges":[{"source":"0","target":"20","id":"5410","attributes":{},"color":"rgb(71,255,249)","size":1.0},{"source":"22","target":"44","id":"5458","attributes":{},"color":"rgb(71,255,249)","size":1.0},{"source":"32","target":"34","id":"5474","attributes":{},"color":"rgb(71,255,249)","size":1.0},{"source":"40","target":"44","id":"5490","attributes":{},"color":"rgb(71,255,249)","size":1.0},{"source":"29","target":"37","id":"5469","attributes":{},"color":"rgb(71,255,249)","size":1.0},{"source":"27","target":"41","id":"5465","attributes":{},"color":"rgb(71,255,249)","size":1.0},{"source":"0","target":"13","id":"5403","attributes":{},"color":"rgb(71,255,249)","size":1.0},{"source":"0","target":"40","id":"5430","attributes":{},"color":"rgb(71,255,249)","size":1.0},{"source":"0","target":"38","id":"5428","attributes":{},"color":"rgb(71,255,249)","size":1.0},{"source":"22","target":"43","id":"5459","attributes":{},"color":"rgb(71,255,249)","size":1.0},{"source":"14","target":"34","id":"5450","attributes":{},"color":"rgb(71,255,249)","size":1.0},{"source":"43","target":"44","id":"5506","attributes":{},"color":"rgb(71,255,249)","size":1.0},{"source":"14","target":"42","id":"5446","attributes":{},"color":"rgb(71,255,249)","size":1.0},{"source":"0","target":"42","id":"5432","attributes":{},"color":"rgb(71,255,249)","size":1.0},{"source":"34","target":"30","id":"5485","attributes":{},"color":"rgb(71,255,249)","size":1.0},{"source":"43","target":"20","id":"5505","attributes":{},"color":"rgb(71,255,249)","size":1.0},{"source":"13","target":"12","id":"5445","attributes":{},"color":"rgb(71,255,249)","size":1.0},{"source":"43","target":"34","id":"5503","attributes":{},"color":"rgb(71,255,249)","size":1.0},{"source":"30","target":"34","id":"5471","attributes":{},"color":"rgb(71,255,249)","size":1.0},{"source":"42","target":"15","id":"5496","attributes":{},"color":"rgb(71,255,249)","size":1.0},{"source":"44","target":"43","id":"5510","attributes":{},"color":"rgb(71,255,249)","size":1.0},{"source":"30","target":"44","id":"5472","attributes":{},"color":"rgb(71,255,249)","size":1.0},{"source":"7","target":"6","id":"5438","attributes":{},"color":"rgb(71,255,249)","size":1.0},{"source":"13","target":"42","id":"5444","attributes":{},"color":"rgb(71,255,249)","size":1.0},{"source":"32","target":"11","id":"5475","attributes":{},"color":"rgb(71,255,249)","size":1.0},{"source":"0","target":"10","id":"5400","attributes":{},"color":"rgb(71,255,249)","size":1.0},{"source":"36","target":"0","id":"5488","attributes":{},"color":"rgb(71,255,249)","size":1.0},{"source":"0","target":"25","id":"5415","attributes":{},"color":"rgb(71,255,249)","size":1.0},{"source":"0","target":"44","id":"5434","attributes":{},"color":"rgb(71,255,249)","size":1.0},{"source":"42","target":"44","id":"5491","attributes":{},"color":"rgb(71,255,249)","size":1.0},{"source":"31","target":"21","id":"5473","attributes":{},"color":"rgb(71,255,249)","size":1.0},{"source":"15","target":"34","id":"5454","attributes":{},"color":"rgb(71,255,249)","size":1.0},{"source":"32","target":"43","id":"5477","attributes":{},"color":"rgb(71,255,249)","size":1.0},{"source":"42","target":"43","id":"5492","attributes":{},"color":"rgb(71,255,249)","size":1.0},{"source":"44","target":"34","id":"5511","attributes":{},"color":"rgb(71,255,249)","size":1.0},{"source":"0","target":"6","id":"5396","attributes":{},"color":"rgb(71,255,249)","size":1.0},{"source":"33","target":"43","id":"5483","attributes":{},"color":"rgb(71,255,249)","size":1.0},{"source":"0","target":"17","id":"5407","attributes":{},"color":"rgb(71,255,249)","size":1.0},{"source":"0","target":"23","id":"5413","attributes":{},"color":"rgb(71,255,249)","size":1.0},{"source":"24","target":"43","id":"5464","attributes":{},"color":"rgb(71,255,249)","size":1.0},{"source":"0","target":"18","id":"5408","attributes":{},"color":"rgb(71,255,249)","size":1.0},{"source":"0","target":"21","id":"5411","attributes":{},"color":"rgb(71,255,249)","size":1.0},{"source":"0","target":"22","id":"5412","attributes":{},"color":"rgb(71,255,249)","size":1.0},{"source":"17","target":"31","id":"5456","attributes":{},"color":"rgb(71,255,249)","size":1.0},{"source":"23","target":"11","id":"5461","attributes":{},"color":"rgb(71,255,249)","size":1.0},{"source":"43","target":"37","id":"5502","attributes":{},"color":"rgb(71,255,249)","size":1.0},{"source":"22","target":"23","id":"5460","attributes":{},"color":"rgb(71,255,249)","size":1.0},{"source":"23","target":"44","id":"5462","attributes":{},"color":"rgb(71,255,249)","size":1.0},{"source":"39","target":"0","id":"5489","attributes":{},"color":"rgb(71,255,249)","size":1.0},{"source":"0","target":"1","id":"5391","attributes":{},"color":"rgb(71,255,249)","size":1.0},{"source":"33","target":"40","id":"5480","attributes":{},"color":"rgb(71,255,249)","size":1.0},{"source":"0","target":"15","id":"5405","attributes":{},"color":"rgb(71,255,249)","size":1.0},{"source":"0","target":"29","id":"5419","attributes":{},"color":"rgb(71,255,249)","size":1.0},{"source":"42","target":"34","id":"5498","attributes":{},"color":"rgb(71,255,249)","size":1.0},{"source":"6","target":"9","id":"5436","attributes":{},"color":"rgb(71,255,249)","size":1.0},{"source":"0","target":"37","id":"5427","attributes":{},"color":"rgb(71,255,249)","size":1.0},{"source":"0","target":"30","id":"5420","attributes":{},"color":"rgb(71,255,249)","size":1.0},{"source":"42","target":"14","id":"5494","attributes":{},"color":"rgb(71,255,249)","size":1.0},{"source":"0","target":"5","id":"5395","attributes":{},"color":"rgb(71,255,249)","size":1.0},{"source":"0","target":"7","id":"5397","attributes":{},"color":"rgb(71,255,249)","size":1.0},{"source":"9","target":"5","id":"5441","attributes":{},"color":"rgb(71,255,249)","size":1.0},{"source":"11","target":"23","id":"5443","attributes":{},"color":"rgb(71,255,249)","size":1.0},{"source":"0","target":"43","id":"5433","attributes":{},"color":"rgb(71,255,249)","size":1.0},{"source":"0","target":"27","id":"5417","attributes":{},"color":"rgb(71,255,249)","size":1.0},{"source":"34","target":"44","id":"5486","attributes":{},"color":"rgb(71,255,249)","size":1.0},{"source":"0","target":"35","id":"5425","attributes":{},"color":"rgb(71,255,249)","size":1.0},{"source":"15","target":"40","id":"5452","attributes":{},"color":"rgb(71,255,249)","size":1.0},{"source":"0","target":"4","id":"5394","attributes":{},"color":"rgb(71,255,249)","size":1.0},{"source":"0","target":"19","id":"5409","attributes":{},"color":"rgb(71,255,249)","size":1.0},{"source":"0","target":"12","id":"5402","attributes":{},"color":"rgb(71,255,249)","size":1.0},{"source":"32","target":"23","id":"5479","attributes":{},"color":"rgb(71,255,249)","size":1.0},{"source":"9","target":"6","id":"5442","attributes":{},"color":"rgb(71,255,249)","size":1.0},{"source":"32","target":"31","id":"5476","attributes":{},"color":"rgb(71,255,249)","size":1.0},{"source":"0","target":"8","id":"5398","attributes":{},"color":"rgb(71,255,249)","size":1.0},{"source":"0","target":"26","id":"5416","attributes":{},"color":"rgb(71,255,249)","size":1.0},{"source":"32","target":"44","id":"5478","attributes":{},"color":"rgb(71,255,249)","size":1.0},{"source":"44","target":"33","id":"5508","attributes":{},"color":"rgb(71,255,249)","size":1.0},{"source":"44","target":"32","id":"5509","attributes":{},"color":"rgb(71,255,249)","size":1.0},{"source":"42","target":"41","id":"5493","attributes":{},"color":"rgb(71,255,249)","size":1.0},{"source":"0","target":"41","id":"5431","attributes":{},"color":"rgb(71,255,249)","size":1.0},{"source":"43","target":"29","id":"5504","attributes":{},"color":"rgb(71,255,249)","size":1.0},{"source":"23","target":"32","id":"5463","attributes":{},"color":"rgb(71,255,249)","size":1.0},{"source":"43","target":"23","id":"5499","attributes":{},"color":"rgb(71,255,249)","size":1.0},{"source":"0","target":"14","id":"5404","attributes":{},"color":"rgb(71,255,249)","size":1.0},{"source":"7","target":"5","id":"5439","attributes":{},"color":"rgb(71,255,249)","size":1.0},{"source":"15","target":"31","id":"5451","attributes":{},"color":"rgb(71,255,249)","size":1.0},{"source":"0","target":"33","id":"5423","attributes":{},"color":"rgb(71,255,249)","size":1.0},{"source":"14","target":"41","id":"5448","attributes":{},"color":"rgb(71,255,249)","size":1.0},{"source":"0","target":"9","id":"5399","attributes":{},"color":"rgb(71,255,249)","size":1.0},{"source":"6","target":"5","id":"5437","attributes":{},"color":"rgb(71,255,249)","size":1.0},{"source":"33","target":"31","id":"5484","attributes":{},"color":"rgb(71,255,249)","size":1.0},{"source":"14","target":"31","id":"5449","attributes":{},"color":"rgb(71,255,249)","size":1.0},{"source":"0","target":"3","id":"5393","attributes":{},"color":"rgb(71,255,249)","size":1.0},{"source":"0","target":"11","id":"5401","attributes":{},"color":"rgb(71,255,249)","size":1.0},{"source":"30","target":"29","id":"5470","attributes":{},"color":"rgb(71,255,249)","size":1.0},{"source":"27","target":"0","id":"5466","attributes":{},"color":"rgb(71,255,249)","size":1.0},{"source":"33","target":"34","id":"5482","attributes":{},"color":"rgb(71,255,249)","size":1.0},{"source":"34","target":"14","id":"5487","attributes":{},"color":"rgb(71,255,249)","size":1.0},{"source":"42","target":"37","id":"5497","attributes":{},"color":"rgb(71,255,249)","size":1.0},{"source":"0","target":"16","id":"5406","attributes":{},"color":"rgb(71,255,249)","size":1.0},{"source":"0","target":"28","id":"5418","attributes":{},"color":"rgb(71,255,249)","size":1.0},{"source":"0","target":"24","id":"5414","attributes":{},"color":"rgb(71,255,249)","size":1.0},{"source":"28","target":"0","id":"5468","attributes":{},"color":"rgb(71,255,249)","size":1.0},{"source":"15","target":"14","id":"5453","attributes":{},"color":"rgb(71,255,249)","size":1.0},{"source":"0","target":"39","id":"5429","attributes":{},"color":"rgb(71,255,249)","size":1.0},{"source":"15","target":"42","id":"5455","attributes":{},"color":"rgb(71,255,249)","size":1.0},{"source":"42","target":"10","id":"5495","attributes":{},"color":"rgb(71,255,249)","size":1.0},{"source":"0","target":"32","id":"5422","attributes":{},"color":"rgb(71,255,249)","size":1.0},{"source":"14","target":"43","id":"5447","attributes":{},"color":"rgb(71,255,249)","size":1.0},{"source":"3","target":"9","id":"5435","attributes":{},"color":"rgb(71,255,249)","size":1.0},{"source":"21","target":"31","id":"5457","attributes":{},"color":"rgb(71,255,249)","size":1.0},{"source":"33","target":"44","id":"5481","attributes":{},"color":"rgb(71,255,249)","size":1.0},{"source":"28","target":"25","id":"5467","attributes":{},"color":"rgb(71,255,249)","size":1.0},{"source":"7","target":"9","id":"5440","attributes":{},"color":"rgb(71,255,249)","size":1.0},{"source":"43","target":"19","id":"5501","attributes":{},"color":"rgb(71,255,249)","size":1.0},{"source":"0","target":"31","id":"5421","attributes":{},"color":"rgb(71,255,249)","size":1.0},{"source":"43","target":"33","id":"5500","attributes":{},"color":"rgb(71,255,249)","size":1.0},{"source":"0","target":"2","id":"5392","attributes":{},"color":"rgb(71,255,249)","size":1.0},{"source":"44","target":"31","id":"5507","attributes":{},"color":"rgb(71,255,249)","size":1.0},{"source":"0","target":"36","id":"5426","attributes":{},"color":"rgb(71,255,249)","size":1.0},{"source":"0","target":"34","id":"5424","attributes":{},"color":"rgb(71,255,249)","size":1.0}]}