{"nodes":[{"label":"Carlos Lupi","x":-758.837158203125,"y":655.6893920898438,"id":"45","attributes":{"post_activity":"0.01","fan_count":"2388","link":"https://www.facebook.com/LupiPDT/","talking_about_count":"15","users_can_post":"no","category":"Politician","username":"LupiPDT"},"color":"rgb(0,2,163)","size":11.0},{"label":"Cadeg - Mercado Municipal Do Rio De Janeiro","x":254.59898376464844,"y":-958.8229370117188,"id":"68","attributes":{"post_activity":"0.03","fan_count":"37806","link":"https://www.facebook.com/CadegMercadoMunicipalDoRioDeJaneiro/","talking_about_count":"1673","users_can_post":"no","category":"Shopping/Retail","username":"CadegMercadoMunicipalDoRioDeJaneiro"},"color":"rgb(0,2,163)","size":25.285715103149414},{"label":"Thallo","x":-739.3536987304688,"y":486.4548645019531,"id":"58","attributes":{"post_activity":"0.0","fan_count":"4954","link":"https://www.facebook.com/Thallo.10670/","talking_about_count":"18","users_can_post":"yes","category":"Entrepreneur","username":"Thallo.10670"},"color":"rgb(0,2,163)","size":11.0},{"label":"Arquidiocese de São Sebastião do Rio de Janeiro","x":-730.0349731445312,"y":819.964111328125,"id":"26","attributes":{"post_activity":"0.38","fan_count":"248092","link":"https://www.facebook.com/arqrio/","talking_about_count":"19151","users_can_post":"yes","category":"Church/Religious Organization","username":"arqrio"},"color":"rgb(0,2,163)","size":11.0},{"label":"Bom Gosto","x":-37.30868911743164,"y":584.154052734375,"id":"61","attributes":{"post_activity":"0.16","fan_count":"2354567","link":"https://www.facebook.com/BomGosto/","talking_about_count":"6254","users_can_post":"no","category":"Musician/Band","username":"BomGosto"},"color":"rgb(0,2,163)","size":18.14285659790039},{"label":"BRT Rio","x":1273.1136474609375,"y":8.17992115020752,"id":"69","attributes":{"post_activity":"0.55","fan_count":"206775","link":"https://www.facebook.com/BRTRioOficial/","talking_about_count":"3230","users_can_post":"yes","category":"Cargo \u0026 Freight Company","username":"BRTRioOficial"},"color":"rgb(0,2,163)","size":18.14285659790039},{"label":"Eduardo Paes","x":621.5620727539062,"y":-221.1544647216797,"id":"39","attributes":{"post_activity":"0.05","fan_count":"129901","link":"https://www.facebook.com/eduardopaesRJ/","talking_about_count":"15642","users_can_post":"no","category":"Politician","username":"eduardopaesRJ"},"color":"rgb(0,2,163)","size":82.42857360839844},{"label":"CUFA - Central Única das Favelas","x":-819.806396484375,"y":554.1401977539062,"id":"14","attributes":{"post_activity":"0.1","fan_count":"26215","link":"https://www.facebook.com/cufabr/","talking_about_count":"202","users_can_post":"no","category":"Non-Profit Organization","username":"cufabr"},"color":"rgb(0,2,163)","size":11.0},{"label":"Rio 450","x":709.5759887695312,"y":-868.4511108398438,"id":"27","attributes":{"post_activity":"0.02","fan_count":"23930","link":"https://www.facebook.com/Rio450/","talking_about_count":"32","users_can_post":"no","category":"Organization","username":"Rio450"},"color":"rgb(0,2,163)","size":53.85714340209961},{"label":"Dionisio Lins","x":-558.9608154296875,"y":785.1519775390625,"id":"37","attributes":{"post_activity":"0.04","fan_count":"16711","link":"https://www.facebook.com/dionisiolinsoficial/","talking_about_count":"233","users_can_post":"yes","category":"Politician","username":"dionisiolinsoficial"},"color":"rgb(0,2,163)","size":11.0},{"label":"PMDB Nacional","x":219.47561645507812,"y":-597.4175415039062,"id":"65","attributes":{"post_activity":"0.13","fan_count":"57826","link":"https://www.facebook.com/PMDBNacional15/","talking_about_count":"3235","users_can_post":"no","category":"Political Party","username":"PMDBNacional15"},"color":"rgb(0,2,163)","size":18.14285659790039},{"label":"Museu de Arte do Rio","x":1097.2215576171875,"y":-840.5714111328125,"id":"17","attributes":{"post_activity":"0.06","fan_count":"148154","link":"https://www.facebook.com/museudeartedorio/","talking_about_count":"7959","users_can_post":"no","category":"Museum/Art Gallery","username":"museudeartedorio"},"color":"rgb(0,2,163)","size":53.85714340209961},{"label":"Rio Resiliente","x":1345.2503662109375,"y":-371.9694519042969,"id":"28","attributes":{"post_activity":"0.01","fan_count":"3796","link":"https://www.facebook.com/rioresiliente/","talking_about_count":"11","users_can_post":"no","category":"Government Organization","username":"rioresiliente"},"color":"rgb(0,2,163)","size":32.42857360839844},{"label":"Rodrigo [Minotauro] Nogueira","x":-1138.8345947265625,"y":1052.2388916015625,"id":"33","attributes":{"post_activity":"0.09","fan_count":"1781607","link":"https://www.facebook.com/minotauromma/","talking_about_count":"29073","users_can_post":"no","category":"Athlete","username":"minotauromma"},"color":"rgb(0,2,163)","size":18.14285659790039},{"label":"Visit.Rio - Riotur","x":564.5156860351562,"y":-736.0447387695312,"id":"2","attributes":{"post_activity":"0.14","fan_count":"99804","link":"https://www.facebook.com/riodejaneiro/","talking_about_count":"2307","users_can_post":"yes","category":"Tours/Sightseeing","username":"riodejaneiro"},"color":"rgb(0,2,163)","size":61.0},{"label":"Babilonia Rio Hostel","x":-46.48017501831055,"y":-590.2062377929688,"id":"13","attributes":{"post_activity":"0.02","fan_count":"3184","link":"https://www.facebook.com/BabiloniaRioHostel/","talking_about_count":"173","users_can_post":"yes","category":"Hotel","username":"BabiloniaRioHostel"},"color":"rgb(0,2,163)","size":11.0},{"label":"Rock in Rio","x":187.0503692626953,"y":-417.6353759765625,"id":"16","attributes":{"post_activity":"0.05","fan_count":"3555603","link":"https://www.facebook.com/RockInRio/","talking_about_count":"9487","users_can_post":"no","category":"Concert Venue","username":"RockInRio"},"color":"rgb(0,2,163)","size":18.14285659790039},{"label":"Fundação Mundo Azul - Grupo de Pais","x":-874.7130126953125,"y":456.04998779296875,"id":"15","attributes":{"post_activity":"0.04","fan_count":"13392","link":"https://www.facebook.com/Fundação-Mundo-Azul-Grupo-de-Pais-176559249216879/","talking_about_count":"252","users_can_post":"no","category":"Non-Profit Organization"},"color":"rgb(0,2,163)","size":11.0},{"label":"Nelson Sargento","x":-952.1686401367188,"y":568.5001220703125,"id":"20","attributes":{"post_activity":"0.04","fan_count":"11008","link":"https://www.facebook.com/nelson.sargento/","talking_about_count":"4417","users_can_post":"yes","category":"Artist","username":"nelson.sargento"},"color":"rgb(0,2,163)","size":11.0},{"label":"Edson Zanata","x":-622.0919799804688,"y":-783.1498413085938,"id":"53","attributes":{"post_activity":"0.04","fan_count":"13970","link":"https://www.facebook.com/edsonzanatarj/","talking_about_count":"347","users_can_post":"yes","category":"Public Figure","username":"edsonzanatarj"},"color":"rgb(0,2,163)","size":18.14285659790039},{"label":"Comitê Paralímpico Brasileiro - CPB","x":839.1243286132812,"y":834.1071166992188,"id":"1","attributes":{"post_activity":"0.27","fan_count":"218829","link":"https://www.facebook.com/ComiteParalimpico/","talking_about_count":"37603","users_can_post":"yes","category":"Non-Profit Organization","username":"ComiteParalimpico"},"color":"rgb(0,2,163)","size":46.71428680419922},{"label":"Vereadora Leila do Flamengo","x":-519.4410400390625,"y":892.0546264648438,"id":"40","attributes":{"post_activity":"0.07","fan_count":"1476","link":"https://www.facebook.com/vereadoraleiladoflamengo/","talking_about_count":"224","users_can_post":"no","category":"Public Figure","username":"vereadoraleiladoflamengo"},"color":"rgb(0,2,163)","size":11.0},{"label":"Jornal O Dia","x":-107.79531860351562,"y":-912.3634033203125,"id":"67","attributes":{"post_activity":"0.76","fan_count":"468192","link":"https://www.facebook.com/odiajornal/","talking_about_count":"35384","users_can_post":"no","category":"News/Media Website","username":"odiajornal"},"color":"rgb(0,2,163)","size":25.285715103149414},{"label":"Portela","x":-330.7877502441406,"y":-816.2174072265625,"id":"63","attributes":{"post_activity":"0.26","fan_count":"226191","link":"https://www.facebook.com/PortelaNoAr/","talking_about_count":"20166","users_can_post":"yes","category":"Arts/Entertainment/Nightlife","username":"PortelaNoAr"},"color":"rgb(0,2,163)","size":32.42857360839844},{"label":"Mauro Diniz","x":-1113.4359130859375,"y":-402.3027038574219,"id":"29","attributes":{"post_activity":"0.04","fan_count":"25129","link":"https://www.facebook.com/maurodinizoficiall/","talking_about_count":"3840","users_can_post":"yes","category":"Artist","username":"maurodinizoficiall"},"color":"rgb(0,2,163)","size":11.0},{"label":"Nelson Sargento","x":-805.4920654296875,"y":368.80853271484375,"id":"21","attributes":{"post_activity":"0.0","fan_count":"17448","link":"https://www.facebook.com/pages/Nelson-Sargento/145387025527892","talking_about_count":"0","users_can_post":"no","category":"Interest"},"color":"rgb(0,2,163)","size":11.0},{"label":"Ancelmo Gois","x":-630.9850463867188,"y":876.4725341796875,"id":"70","attributes":{"post_activity":"0.29","fan_count":"62439","link":"https://www.facebook.com/AncelmoGoisOGlobo/","talking_about_count":"4684","users_can_post":"no","category":"Journalist","username":"AncelmoGoisOGlobo"},"color":"rgb(0,2,163)","size":11.0},{"label":"John Tory","x":-887.9606323242188,"y":653.0594482421875,"id":"9","attributes":{"post_activity":"0.09","fan_count":"33658","link":"https://www.facebook.com/johntoryTO/","talking_about_count":"1718","users_can_post":"no","category":"Politician","username":"johntoryTO"},"color":"rgb(0,2,163)","size":11.0},{"label":"PMDB RJ","x":137.96768188476562,"y":-708.879150390625,"id":"66","attributes":{"post_activity":"0.04","fan_count":"8442","link":"https://www.facebook.com/pmdbrj/","talking_about_count":"1177","users_can_post":"yes","category":"Political Party","username":"pmdbrj"},"color":"rgb(0,2,163)","size":18.14285659790039},{"label":"Museu do Amanhã","x":1290.1583251953125,"y":-653.5454711914062,"id":"4","attributes":{"post_activity":"0.06","fan_count":"101294","link":"https://www.facebook.com/museudoamanha/","talking_about_count":"18867","users_can_post":"no","category":"Museum/Art Gallery","username":"museudoamanha"},"color":"rgb(0,2,163)","size":46.71428680419922},{"label":"SUPER RÁDIO TUPI","x":-619.94189453125,"y":-590.1683349609375,"id":"71","attributes":{"post_activity":"1.2","fan_count":"233375","link":"https://www.facebook.com/radiotupi/","talking_about_count":"19791","users_can_post":"yes","category":"Radio Station","username":"radiotupi"},"color":"rgb(0,2,163)","size":18.14285659790039},{"label":"Vereador Zico","x":-744.7549438476562,"y":-392.19482421875,"id":"54","attributes":{"post_activity":"0.02","fan_count":"6071","link":"https://www.facebook.com/vereadorzico/","talking_about_count":"63","users_can_post":"no","category":"Politician","username":"vereadorzico"},"color":"rgb(0,2,163)","size":18.14285659790039},{"label":"Marcelo D2","x":-322.1963806152344,"y":-357.8891296386719,"id":"51","attributes":{"post_activity":"0.04","fan_count":"3684340","link":"https://www.facebook.com/marcelodedois/","talking_about_count":"17569","users_can_post":"no","category":"Musician/Band","username":"marcelodedois"},"color":"rgb(0,2,163)","size":18.14285659790039},{"label":"Vereadora Fatinha","x":-989.947998046875,"y":467.58941650390625,"id":"59","attributes":{"post_activity":"0.06","fan_count":"2249","link":"https://www.facebook.com/fatinhavereadora.com.br/","talking_about_count":"269","users_can_post":"yes","category":"Politician","username":"fatinhavereadora.com.br"},"color":"rgb(0,2,163)","size":11.0},{"label":"Luiz Fernando Pezão","x":-73.40013122558594,"y":-289.2729797363281,"id":"38","attributes":{"post_activity":"0.01","fan_count":"220796","link":"https://www.facebook.com/LFPezao/","talking_about_count":"419","users_can_post":"no","category":"Politician","username":"LFPezao"},"color":"rgb(0,2,163)","size":53.85714340209961},{"label":"Prefeitura do Rio de Janeiro","x":923.6649780273438,"y":-506.63934326171875,"id":"10","attributes":{"post_activity":"0.09","fan_count":"181394","link":"https://www.facebook.com/PrefeituradoRio/","talking_about_count":"20731","users_can_post":"no","category":"Government Organization","username":"PrefeituradoRio"},"color":"rgb(0,2,163)","size":103.85713958740234},{"label":"Deputado Estadual Rafael do Gordo","x":-526.85009765625,"y":-250.73597717285156,"id":"49","attributes":{"post_activity":"0.02","fan_count":"1801","link":"https://www.facebook.com/dep.rafaeldogordo/","talking_about_count":"1","users_can_post":"no","category":"Politician","username":"dep.rafaeldogordo"},"color":"rgb(0,2,163)","size":11.0},{"label":"Pedro Fernandes","x":-1010.7546997070312,"y":-485.3171691894531,"id":"35","attributes":{"post_activity":"0.03","fan_count":"9912","link":"https://www.facebook.com/deputado.pedrofernandes/","talking_about_count":"230","users_can_post":"yes","category":"Politician","username":"deputado.pedrofernandes"},"color":"rgb(0,2,163)","size":18.14285659790039},{"label":"Tiago Mohamed","x":-904.7242431640625,"y":325.0508728027344,"id":"52","attributes":{"post_activity":"0.05","fan_count":"13048","link":"https://www.facebook.com/tiagomohamedrj/","talking_about_count":"54","users_can_post":"yes","category":"Public Figure","username":"tiagomohamedrj"},"color":"rgb(0,2,163)","size":11.0},{"label":"Pedro Paulo","x":-311.4842834472656,"y":203.3236083984375,"id":"0","attributes":{"post_activity":"0.09","fan_count":"56329","link":"https://www.facebook.com/rio.pedropaulo/","talking_about_count":"10951","users_can_post":"no","category":"Politician","username":"rio.pedropaulo"},"color":"rgb(0,2,163)","size":46.71428680419922},{"label":"Estação Primeira de Mangueira","x":-1060.3558349609375,"y":-241.46177673339844,"id":"24","attributes":{"post_activity":"0.1","fan_count":"157128","link":"https://www.facebook.com/GRESEPMangueira/","talking_about_count":"9028","users_can_post":"yes","category":"Arts/Entertainment/Nightlife","username":"GRESEPMangueira"},"color":"rgb(0,2,163)","size":18.14285659790039},{"label":"Mocidade Independente de Padre Miguel","x":-872.2861328125,"y":100.40103149414062,"id":"22","attributes":{"post_activity":"0.08","fan_count":"159076","link":"https://www.facebook.com/MocidadeOficial/","talking_about_count":"7084","users_can_post":"no","category":"Arts/Entertainment/Nightlife","username":"MocidadeOficial"},"color":"rgb(0,2,163)","size":11.0},{"label":"Zico - Arthur Antunes Coimbra","x":60.334266662597656,"y":879.0257568359375,"id":"19","attributes":{"post_activity":"0.31","fan_count":"2681654","link":"https://www.facebook.com/ZicoOficial/","talking_about_count":"60921","users_can_post":"yes","category":"Athlete","username":"ZicoOficial"},"color":"rgb(0,2,163)","size":25.285715103149414},{"label":"Eu Voto 1515","x":-374.3065490722656,"y":793.4614868164062,"id":"31","attributes":{"post_activity":"0.0","fan_count":"298","link":"https://www.facebook.com/euvoto1515/","talking_about_count":"9","users_can_post":"yes","category":"App Page","username":"euvoto1515"},"color":"rgb(0,2,163)","size":11.0},{"label":"G.R.Cacique de Ramos","x":-1592.3248291015625,"y":37.486602783203125,"id":"55","attributes":{"post_activity":"0.24","fan_count":"44443","link":"https://www.facebook.com/GRCacique-de-Ramos-251464291568256/","talking_about_count":"17115","users_can_post":"no","category":"Society/Culture Website"},"color":"rgb(0,2,163)","size":25.285715103149414},{"label":"Marcelo Arar","x":-1010.0861206054688,"y":371.0802001953125,"id":"62","attributes":{"post_activity":"0.02","fan_count":"63528","link":"https://www.facebook.com/marceloararoficial/","talking_about_count":"2190","users_can_post":"no","category":"Public Figure","username":"marceloararoficial"},"color":"rgb(0,2,163)","size":11.0},{"label":"Unidos do Viradouro","x":-668.277099609375,"y":735.343017578125,"id":"23","attributes":{"post_activity":"0.02","fan_count":"23371","link":"https://www.facebook.com/unidosviradouro/","talking_about_count":"556","users_can_post":"no","category":"Arts/Entertainment/Nightlife","username":"unidosviradouro"},"color":"rgb(0,2,163)","size":11.0},{"label":"Deputada Lucinha","x":-576.4186401367188,"y":659.862060546875,"id":"43","attributes":{"post_activity":"0.05","fan_count":"3600","link":"https://www.facebook.com/lucinhafaz/","talking_about_count":"222","users_can_post":"yes","category":"Politician","username":"lucinhafaz"},"color":"rgb(0,2,163)","size":11.0},{"label":"Cidade Olímpica","x":1089.109375,"y":-210.33973693847656,"id":"18","attributes":{"post_activity":"0.1","fan_count":"277496","link":"https://www.facebook.com/CidadeOlimpica/","talking_about_count":"4451","users_can_post":"no","category":"Government Organization","username":"CidadeOlimpica"},"color":"rgb(0,2,163)","size":111.0},{"label":"Atendimento Ao Cidadão","x":484.199951171875,"y":342.0052795410156,"id":"34","attributes":{"post_activity":"0.0","fan_count":"17121","link":"https://www.facebook.com/Central1746/","talking_about_count":"54","users_can_post":"no","category":"Government Organization","username":"Central1746"},"color":"rgb(0,2,163)","size":32.42857360839844},{"label":"O Explicador","x":1173.7340087890625,"y":82.62916564941406,"id":"3","attributes":{"post_activity":"0.01","fan_count":"141805","link":"https://www.facebook.com/oexplicadorprefeitura/","talking_about_count":"100","users_can_post":"no","category":"Public Figure","username":"oexplicadorprefeitura"},"color":"rgb(0,2,163)","size":53.85714340209961},{"label":"Edênia Garcia","x":615.13037109375,"y":1052.2171630859375,"id":"6","attributes":{"post_activity":"0.04","fan_count":"6390","link":"https://www.facebook.com/fapageedeniagarcia/","talking_about_count":"517","users_can_post":"no","category":"Athlete","username":"fapageedeniagarcia"},"color":"rgb(0,2,163)","size":18.14285659790039},{"label":"Paulo Messina","x":-951.1796875,"y":167.96482849121094,"id":"56","attributes":{"post_activity":"0.02","fan_count":"32963","link":"https://www.facebook.com/sitedomessina/","talking_about_count":"727","users_can_post":"yes","category":"Politician","username":"sitedomessina"},"color":"rgb(0,2,163)","size":11.0},{"label":"Fã Clube Império Serrano","x":-843.801025390625,"y":229.11361694335938,"id":"64","attributes":{"post_activity":"0.0","fan_count":"13759","link":"https://www.facebook.com/faclubeImperioSerrano/","talking_about_count":"16","users_can_post":"no","category":"Arts/Entertainment/Nightlife","username":"faclubeImperioSerrano"},"color":"rgb(0,2,163)","size":11.0},{"label":"Sandra de Sá","x":-471.6260986328125,"y":734.7653198242188,"id":"36","attributes":{"post_activity":"0.19","fan_count":"561128","link":"https://www.facebook.com/sandra.desa.520/","talking_about_count":"95538","users_can_post":"yes","category":"Musician/Band","username":"sandra.desa.520"},"color":"rgb(0,2,163)","size":11.0},{"label":"Teco Padaratz","x":-819.009765625,"y":744.9832153320312,"id":"30","attributes":{"post_activity":"0.0","fan_count":"1276","link":"https://www.facebook.com/Teco-Padaratz-160484110675270/","talking_about_count":"4","users_can_post":"no","category":"Athlete"},"color":"rgb(0,2,163)","size":11.0},{"label":"Rio de Janeiro, Brazil","x":-269.9862976074219,"y":-577.9413452148438,"id":"25","attributes":{"post_activity":"0.0","fan_count":"2181213","link":"https://www.facebook.com/pages/Rio-de-Janeiro-Brazil/110346955653479","talking_about_count":"0","users_can_post":"yes","category":"City"},"color":"rgb(0,2,163)","size":32.42857360839844},{"label":"Vereadora Rosa Fernandes","x":-972.279541015625,"y":-641.946533203125,"id":"44","attributes":{"post_activity":"0.01","fan_count":"23171","link":"https://www.facebook.com/vereadorarosafernandesrj/","talking_about_count":"185","users_can_post":"yes","category":"Politician","username":"vereadorarosafernandesrj"},"color":"rgb(0,2,163)","size":25.285715103149414},{"label":"Secretaria Municipal da Pessoa com Deficiência - SMPD","x":879.9437866210938,"y":129.2022247314453,"id":"12","attributes":{"post_activity":"0.11","fan_count":"4207","link":"https://www.facebook.com/SMPDRJ/","talking_about_count":"453","users_can_post":"no","category":"Government Organization","username":"SMPDRJ"},"color":"rgb(0,2,163)","size":39.57143020629883},{"label":"André Ferraz","x":340.96563720703125,"y":-342.3560485839844,"id":"41","attributes":{"post_activity":"0.01","fan_count":"1368","link":"https://www.facebook.com/andreferraz2014/","talking_about_count":"1","users_can_post":"yes","category":"Politician","username":"andreferraz2014"},"color":"rgb(0,2,163)","size":11.0},{"label":"Jorge Felippe Neto","x":431.12689208984375,"y":53.84113693237305,"id":"46","attributes":{"post_activity":"0.05","fan_count":"9615","link":"https://www.facebook.com/jfelippeneto/","talking_about_count":"571","users_can_post":"no","category":"Politician","username":"jfelippeneto"},"color":"rgb(0,2,163)","size":18.14285659790039},{"label":"Conselho da Cidade - Prefeitura do Rio de Janeiro","x":311.3725891113281,"y":625.0302734375,"id":"73","attributes":{"post_activity":"0.0","fan_count":"447","link":"https://www.facebook.com/conselhodacidaderj/","talking_about_count":"0","users_can_post":"yes","category":"Community","username":"conselhodacidaderj"},"color":"rgb(0,2,163)","size":18.14285659790039},{"label":"Clube de Regatas do Flamengo","x":319.6430358886719,"y":1073.434814453125,"id":"11","attributes":{"post_activity":"0.6","fan_count":"10618488","link":"https://www.facebook.com/FlamengoOficial/","talking_about_count":"442355","users_can_post":"no","category":"Sports Team","username":"FlamengoOficial"},"color":"rgb(0,2,163)","size":25.285715103149414},{"label":"Hackathon 1746","x":204.960693359375,"y":372.7286682128906,"id":"72","attributes":{"post_activity":"0.0","fan_count":"325","link":"https://www.facebook.com/hackathon1746/","talking_about_count":"2","users_can_post":"no","category":"Internet/Software","username":"hackathon1746"},"color":"rgb(0,2,163)","size":18.14285659790039},{"label":"Rogério [Minotouro] Nogueira","x":-1199.218505859375,"y":989.6045532226562,"id":"32","attributes":{"post_activity":"0.07","fan_count":"599464","link":"https://www.facebook.com/minotouromma/","talking_about_count":"2761","users_can_post":"no","category":"Athlete","username":"minotouromma"},"color":"rgb(0,2,163)","size":18.14285659790039},{"label":"Beth Carvalho","x":-1507.0294189453125,"y":-121.75211334228516,"id":"60","attributes":{"post_activity":"0.03","fan_count":"1058443","link":"https://www.facebook.com/OficialBethCarvalho/","talking_about_count":"9135","users_can_post":"yes","category":"Musician/Band","username":"OficialBethCarvalho"},"color":"rgb(0,2,163)","size":32.42857360839844},{"label":"Luiz Lima","x":-679.30224609375,"y":595.6600952148438,"id":"42","attributes":{"post_activity":"0.0","fan_count":"147","link":"https://www.facebook.com/pages/Luiz-Lima/105940892770922","talking_about_count":"0","users_can_post":"no","category":"Public Figure"},"color":"rgb(0,2,163)","size":11.0},{"label":"Diogo Ualisson","x":-413.6089782714844,"y":886.4132080078125,"id":"5","attributes":{"post_activity":"0.01","fan_count":"850","link":"https://www.facebook.com/atletadiogoualisson/","talking_about_count":"59","users_can_post":"yes","category":"Athlete","username":"atletadiogoualisson"},"color":"rgb(0,2,163)","size":11.0},{"label":"Terezinha Guilhermina","x":750.3921508789062,"y":1174.1767578125,"id":"8","attributes":{"post_activity":"0.06","fan_count":"15071","link":"https://www.facebook.com/terezinhaguilherminaoficial/","talking_about_count":"697","users_can_post":"yes","category":"Athlete","username":"terezinhaguilherminaoficial"},"color":"rgb(0,2,163)","size":25.285715103149414},{"label":"Andre Brasil","x":875.25830078125,"y":1032.6153564453125,"id":"7","attributes":{"post_activity":"0.02","fan_count":"10386","link":"https://www.facebook.com/andrebrasils10/","talking_about_count":"243","users_can_post":"yes","category":"Athlete","username":"andrebrasils10"},"color":"rgb(0,2,163)","size":39.57143020629883},{"label":"Deputado Thiago Pampolha","x":-4.210102081298828,"y":-10.07463550567627,"id":"47","attributes":{"post_activity":"0.04","fan_count":"41652","link":"https://www.facebook.com/deputadothiagopampolha/","talking_about_count":"75","users_can_post":"yes","category":"Politician","username":"deputadothiagopampolha"},"color":"rgb(0,2,163)","size":11.0},{"label":"Salgado Carioca","x":-998.6257934570312,"y":259.34332275390625,"id":"57","attributes":{"post_activity":"0.01","fan_count":"289","link":"https://www.facebook.com/tiagomohamed15001/","talking_about_count":"1","users_can_post":"yes","category":"Public Figure","username":"tiagomohamed15001"},"color":"rgb(0,2,163)","size":11.0},{"label":"Cantor Mumuzinho","x":169.44784545898438,"y":114.76963806152344,"id":"48","attributes":{"post_activity":"0.31","fan_count":"2398478","link":"https://www.facebook.com/CantorMumuzinho/","talking_about_count":"77880","users_can_post":"yes","category":"Musician/Band","username":"CantorMumuzinho"},"color":"rgb(0,2,163)","size":18.14285659790039},{"label":"Bira Presidente","x":-1478.465087890625,"y":115.68500518798828,"id":"50","attributes":{"post_activity":"0.01","fan_count":"19998","link":"https://www.facebook.com/Bira-Presidente-248440498592392/","talking_about_count":"92","users_can_post":"no","category":"Artist"},"color":"rgb(0,2,163)","size":11.0}],"edges":[{"source":"0","target":"69","id":"5580","attributes":{},"color":"rgb(0,2,163)","size":1.0},{"source":"12","target":"3","id":"5623","attributes":{},"color":"rgb(0,2,163)","size":1.0},{"source":"18","target":"4","id":"5644","attributes":{},"color":"rgb(0,2,163)","size":1.0},{"source":"48","target":"61","id":"5693","attributes":{},"color":"rgb(0,2,163)","size":1.0},{"source":"0","target":"42","id":"5553","attributes":{},"color":"rgb(0,2,163)","size":1.0},{"source":"0","target":"28","id":"5539","attributes":{},"color":"rgb(0,2,163)","size":1.0},{"source":"27","target":"25","id":"5656","attributes":{},"color":"rgb(0,2,163)","size":1.0},{"source":"0","target":"30","id":"5541","attributes":{},"color":"rgb(0,2,163)","size":1.0},{"source":"0","target":"3","id":"5514","attributes":{},"color":"rgb(0,2,163)","size":1.0},{"source":"0","target":"21","id":"5532","attributes":{},"color":"rgb(0,2,163)","size":1.0},{"source":"0","target":"39","id":"5550","attributes":{},"color":"rgb(0,2,163)","size":1.0},{"source":"2","target":"48","id":"5593","attributes":{},"color":"rgb(0,2,163)","size":1.0},{"source":"0","target":"45","id":"5556","attributes":{},"color":"rgb(0,2,163)","size":1.0},{"source":"0","target":"5","id":"5516","attributes":{},"color":"rgb(0,2,163)","size":1.0},{"source":"2","target":"63","id":"5597","attributes":{},"color":"rgb(0,2,163)","size":1.0},{"source":"41","target":"10","id":"5685","attributes":{},"color":"rgb(0,2,163)","size":1.0},{"source":"0","target":"27","id":"5538","attributes":{},"color":"rgb(0,2,163)","size":1.0},{"source":"69","target":"10","id":"5719","attributes":{},"color":"rgb(0,2,163)","size":1.0},{"source":"17","target":"27","id":"5633","attributes":{},"color":"rgb(0,2,163)","size":1.0},{"source":"0","target":"41","id":"5552","attributes":{},"color":"rgb(0,2,163)","size":1.0},{"source":"0","target":"40","id":"5551","attributes":{},"color":"rgb(0,2,163)","size":1.0},{"source":"50","target":"60","id":"5695","attributes":{},"color":"rgb(0,2,163)","size":1.0},{"source":"0","target":"1","id":"5512","attributes":{},"color":"rgb(0,2,163)","size":1.0},{"source":"0","target":"46","id":"5557","attributes":{},"color":"rgb(0,2,163)","size":1.0},{"source":"2","target":"17","id":"5596","attributes":{},"color":"rgb(0,2,163)","size":1.0},{"source":"12","target":"39","id":"5629","attributes":{},"color":"rgb(0,2,163)","size":1.0},{"source":"27","target":"2","id":"5652","attributes":{},"color":"rgb(0,2,163)","size":1.0},{"source":"53","target":"53","id":"5699","attributes":{},"color":"rgb(0,2,163)","size":1.0},{"source":"69","target":"18","id":"5720","attributes":{},"color":"rgb(0,2,163)","size":1.0},{"source":"73","target":"34","id":"5723","attributes":{},"color":"rgb(0,2,163)","size":1.0},{"source":"0","target":"72","id":"5583","attributes":{},"color":"rgb(0,2,163)","size":1.0},{"source":"0","target":"4","id":"5515","attributes":{},"color":"rgb(0,2,163)","size":1.0},{"source":"2","target":"27","id":"5594","attributes":{},"color":"rgb(0,2,163)","size":1.0},{"source":"47","target":"46","id":"5690","attributes":{},"color":"rgb(0,2,163)","size":1.0},{"source":"0","target":"47","id":"5558","attributes":{},"color":"rgb(0,2,163)","size":1.0},{"source":"60","target":"24","id":"5705","attributes":{},"color":"rgb(0,2,163)","size":1.0},{"source":"65","target":"10","id":"5708","attributes":{},"color":"rgb(0,2,163)","size":1.0},{"source":"10","target":"34","id":"5617","attributes":{},"color":"rgb(0,2,163)","size":1.0},{"source":"28","target":"17","id":"5658","attributes":{},"color":"rgb(0,2,163)","size":1.0},{"source":"0","target":"7","id":"5518","attributes":{},"color":"rgb(0,2,163)","size":1.0},{"source":"0","target":"22","id":"5533","attributes":{},"color":"rgb(0,2,163)","size":1.0},{"source":"47","target":"0","id":"5692","attributes":{},"color":"rgb(0,2,163)","size":1.0},{"source":"34","target":"73","id":"5670","attributes":{},"color":"rgb(0,2,163)","size":1.0},{"source":"54","target":"35","id":"5703","attributes":{},"color":"rgb(0,2,163)","size":1.0},{"source":"0","target":"32","id":"5543","attributes":{},"color":"rgb(0,2,163)","size":1.0},{"source":"50","target":"55","id":"5696","attributes":{},"color":"rgb(0,2,163)","size":1.0},{"source":"53","target":"44","id":"5698","attributes":{},"color":"rgb(0,2,163)","size":1.0},{"source":"10","target":"17","id":"5616","attributes":{},"color":"rgb(0,2,163)","size":1.0},{"source":"18","target":"28","id":"5639","attributes":{},"color":"rgb(0,2,163)","size":1.0},{"source":"39","target":"18","id":"5681","attributes":{},"color":"rgb(0,2,163)","size":1.0},{"source":"10","target":"2","id":"5614","attributes":{},"color":"rgb(0,2,163)","size":1.0},{"source":"7","target":"1","id":"5606","attributes":{},"color":"rgb(0,2,163)","size":1.0},{"source":"39","target":"2","id":"5676","attributes":{},"color":"rgb(0,2,163)","size":1.0},{"source":"0","target":"67","id":"5578","attributes":{},"color":"rgb(0,2,163)","size":1.0},{"source":"0","target":"29","id":"5540","attributes":{},"color":"rgb(0,2,163)","size":1.0},{"source":"41","target":"25","id":"5684","attributes":{},"color":"rgb(0,2,163)","size":1.0},{"source":"0","target":"60","id":"5571","attributes":{},"color":"rgb(0,2,163)","size":1.0},{"source":"0","target":"43","id":"5554","attributes":{},"color":"rgb(0,2,163)","size":1.0},{"source":"0","target":"71","id":"5582","attributes":{},"color":"rgb(0,2,163)","size":1.0},{"source":"1","target":"11","id":"5586","attributes":{},"color":"rgb(0,2,163)","size":1.0},{"source":"10","target":"39","id":"5618","attributes":{},"color":"rgb(0,2,163)","size":1.0},{"source":"66","target":"67","id":"5715","attributes":{},"color":"rgb(0,2,163)","size":1.0},{"source":"39","target":"38","id":"5675","attributes":{},"color":"rgb(0,2,163)","size":1.0},{"source":"17","target":"4","id":"5636","attributes":{},"color":"rgb(0,2,163)","size":1.0},{"source":"11","target":"1","id":"5621","attributes":{},"color":"rgb(0,2,163)","size":1.0},{"source":"10","target":"12","id":"5615","attributes":{},"color":"rgb(0,2,163)","size":1.0},{"source":"41","target":"18","id":"5687","attributes":{},"color":"rgb(0,2,163)","size":1.0},{"source":"18","target":"69","id":"5643","attributes":{},"color":"rgb(0,2,163)","size":1.0},{"source":"0","target":"19","id":"5530","attributes":{},"color":"rgb(0,2,163)","size":1.0},{"source":"28","target":"12","id":"5663","attributes":{},"color":"rgb(0,2,163)","size":1.0},{"source":"0","target":"53","id":"5564","attributes":{},"color":"rgb(0,2,163)","size":1.0},{"source":"27","target":"18","id":"5654","attributes":{},"color":"rgb(0,2,163)","size":1.0},{"source":"60","target":"55","id":"5706","attributes":{},"color":"rgb(0,2,163)","size":1.0},{"source":"0","target":"2","id":"5513","attributes":{},"color":"rgb(0,2,163)","size":1.0},{"source":"63","target":"71","id":"5707","attributes":{},"color":"rgb(0,2,163)","size":1.0},{"source":"0","target":"38","id":"5549","attributes":{},"color":"rgb(0,2,163)","size":1.0},{"source":"65","target":"39","id":"5709","attributes":{},"color":"rgb(0,2,163)","size":1.0},{"source":"1","target":"6","id":"5590","attributes":{},"color":"rgb(0,2,163)","size":1.0},{"source":"34","target":"0","id":"5671","attributes":{},"color":"rgb(0,2,163)","size":1.0},{"source":"41","target":"39","id":"5686","attributes":{},"color":"rgb(0,2,163)","size":1.0},{"source":"0","target":"17","id":"5528","attributes":{},"color":"rgb(0,2,163)","size":1.0},{"source":"0","target":"24","id":"5535","attributes":{},"color":"rgb(0,2,163)","size":1.0},{"source":"0","target":"36","id":"5547","attributes":{},"color":"rgb(0,2,163)","size":1.0},{"source":"1","target":"10","id":"5587","attributes":{},"color":"rgb(0,2,163)","size":1.0},{"source":"0","target":"58","id":"5569","attributes":{},"color":"rgb(0,2,163)","size":1.0},{"source":"0","target":"48","id":"5559","attributes":{},"color":"rgb(0,2,163)","size":1.0},{"source":"0","target":"51","id":"5562","attributes":{},"color":"rgb(0,2,163)","size":1.0},{"source":"33","target":"32","id":"5667","attributes":{},"color":"rgb(0,2,163)","size":1.0},{"source":"53","target":"10","id":"5700","attributes":{},"color":"rgb(0,2,163)","size":1.0},{"source":"68","target":"67","id":"5717","attributes":{},"color":"rgb(0,2,163)","size":1.0},{"source":"0","target":"12","id":"5523","attributes":{},"color":"rgb(0,2,163)","size":1.0},{"source":"17","target":"18","id":"5637","attributes":{},"color":"rgb(0,2,163)","size":1.0},{"source":"54","target":"38","id":"5701","attributes":{},"color":"rgb(0,2,163)","size":1.0},{"source":"2","target":"4","id":"5592","attributes":{},"color":"rgb(0,2,163)","size":1.0},{"source":"10","target":"3","id":"5611","attributes":{},"color":"rgb(0,2,163)","size":1.0},{"source":"17","target":"10","id":"5634","attributes":{},"color":"rgb(0,2,163)","size":1.0},{"source":"27","target":"68","id":"5653","attributes":{},"color":"rgb(0,2,163)","size":1.0},{"source":"0","target":"64","id":"5575","attributes":{},"color":"rgb(0,2,163)","size":1.0},{"source":"18","target":"27","id":"5641","attributes":{},"color":"rgb(0,2,163)","size":1.0},{"source":"66","target":"39","id":"5716","attributes":{},"color":"rgb(0,2,163)","size":1.0},{"source":"18","target":"3","id":"5646","attributes":{},"color":"rgb(0,2,163)","size":1.0},{"source":"0","target":"44","id":"5555","attributes":{},"color":"rgb(0,2,163)","size":1.0},{"source":"0","target":"23","id":"5534","attributes":{},"color":"rgb(0,2,163)","size":1.0},{"source":"0","target":"57","id":"5568","attributes":{},"color":"rgb(0,2,163)","size":1.0},{"source":"0","target":"59","id":"5570","attributes":{},"color":"rgb(0,2,163)","size":1.0},{"source":"39","target":"3","id":"5678","attributes":{},"color":"rgb(0,2,163)","size":1.0},{"source":"0","target":"33","id":"5544","attributes":{},"color":"rgb(0,2,163)","size":1.0},{"source":"41","target":"2","id":"5683","attributes":{},"color":"rgb(0,2,163)","size":1.0},{"source":"34","target":"39","id":"5669","attributes":{},"color":"rgb(0,2,163)","size":1.0},{"source":"10","target":"4","id":"5612","attributes":{},"color":"rgb(0,2,163)","size":1.0},{"source":"0","target":"37","id":"5548","attributes":{},"color":"rgb(0,2,163)","size":1.0},{"source":"29","target":"63","id":"5664","attributes":{},"color":"rgb(0,2,163)","size":1.0},{"source":"10","target":"28","id":"5610","attributes":{},"color":"rgb(0,2,163)","size":1.0},{"source":"38","target":"19","id":"5673","attributes":{},"color":"rgb(0,2,163)","size":1.0},{"source":"19","target":"11","id":"5648","attributes":{},"color":"rgb(0,2,163)","size":1.0},{"source":"4","target":"17","id":"5600","attributes":{},"color":"rgb(0,2,163)","size":1.0},{"source":"0","target":"49","id":"5560","attributes":{},"color":"rgb(0,2,163)","size":1.0},{"source":"0","target":"13","id":"5524","attributes":{},"color":"rgb(0,2,163)","size":1.0},{"source":"0","target":"65","id":"5576","attributes":{},"color":"rgb(0,2,163)","size":1.0},{"source":"18","target":"34","id":"5640","attributes":{},"color":"rgb(0,2,163)","size":1.0},{"source":"16","target":"51","id":"5632","attributes":{},"color":"rgb(0,2,163)","size":1.0},{"source":"0","target":"15","id":"5526","attributes":{},"color":"rgb(0,2,163)","size":1.0},{"source":"0","target":"73","id":"5584","attributes":{},"color":"rgb(0,2,163)","size":1.0},{"source":"10","target":"18","id":"5619","attributes":{},"color":"rgb(0,2,163)","size":1.0},{"source":"46","target":"39","id":"5688","attributes":{},"color":"rgb(0,2,163)","size":1.0},{"source":"54","target":"0","id":"5702","attributes":{},"color":"rgb(0,2,163)","size":1.0},{"source":"0","target":"61","id":"5572","attributes":{},"color":"rgb(0,2,163)","size":1.0},{"source":"28","target":"3","id":"5657","attributes":{},"color":"rgb(0,2,163)","size":1.0},{"source":"10","target":"27","id":"5620","attributes":{},"color":"rgb(0,2,163)","size":1.0},{"source":"35","target":"44","id":"5672","attributes":{},"color":"rgb(0,2,163)","size":1.0},{"source":"0","target":"70","id":"5581","attributes":{},"color":"rgb(0,2,163)","size":1.0},{"source":"16","target":"18","id":"5631","attributes":{},"color":"rgb(0,2,163)","size":1.0},{"source":"13","target":"2","id":"5630","attributes":{},"color":"rgb(0,2,163)","size":1.0},{"source":"24","target":"25","id":"5649","attributes":{},"color":"rgb(0,2,163)","size":1.0},{"source":"0","target":"50","id":"5561","attributes":{},"color":"rgb(0,2,163)","size":1.0},{"source":"27","target":"10","id":"5651","attributes":{},"color":"rgb(0,2,163)","size":1.0},{"source":"18","target":"17","id":"5647","attributes":{},"color":"rgb(0,2,163)","size":1.0},{"source":"0","target":"11","id":"5522","attributes":{},"color":"rgb(0,2,163)","size":1.0},{"source":"1","target":"18","id":"5585","attributes":{},"color":"rgb(0,2,163)","size":1.0},{"source":"2","target":"10","id":"5595","attributes":{},"color":"rgb(0,2,163)","size":1.0},{"source":"28","target":"4","id":"5659","attributes":{},"color":"rgb(0,2,163)","size":1.0},{"source":"66","target":"65","id":"5714","attributes":{},"color":"rgb(0,2,163)","size":1.0},{"source":"0","target":"66","id":"5577","attributes":{},"color":"rgb(0,2,163)","size":1.0},{"source":"29","target":"60","id":"5665","attributes":{},"color":"rgb(0,2,163)","size":1.0},{"source":"0","target":"34","id":"5545","attributes":{},"color":"rgb(0,2,163)","size":1.0},{"source":"0","target":"10","id":"5521","attributes":{},"color":"rgb(0,2,163)","size":1.0},{"source":"12","target":"18","id":"5627","attributes":{},"color":"rgb(0,2,163)","size":1.0},{"source":"0","target":"14","id":"5525","attributes":{},"color":"rgb(0,2,163)","size":1.0},{"source":"12","target":"0","id":"5624","attributes":{},"color":"rgb(0,2,163)","size":1.0},{"source":"8","target":"7","id":"5609","attributes":{},"color":"rgb(0,2,163)","size":1.0},{"source":"0","target":"63","id":"5574","attributes":{},"color":"rgb(0,2,163)","size":1.0},{"source":"69","target":"3","id":"5718","attributes":{},"color":"rgb(0,2,163)","size":1.0},{"source":"0","target":"35","id":"5546","attributes":{},"color":"rgb(0,2,163)","size":1.0},{"source":"18","target":"10","id":"5645","attributes":{},"color":"rgb(0,2,163)","size":1.0},{"source":"0","target":"9","id":"5520","attributes":{},"color":"rgb(0,2,163)","size":1.0},{"source":"4","target":"18","id":"5602","attributes":{},"color":"rgb(0,2,163)","size":1.0},{"source":"11","target":"19","id":"5622","attributes":{},"color":"rgb(0,2,163)","size":1.0},{"source":"17","target":"2","id":"5635","attributes":{},"color":"rgb(0,2,163)","size":1.0},{"source":"4","target":"10","id":"5601","attributes":{},"color":"rgb(0,2,163)","size":1.0},{"source":"38","target":"39","id":"5674","attributes":{},"color":"rgb(0,2,163)","size":1.0},{"source":"0","target":"55","id":"5566","attributes":{},"color":"rgb(0,2,163)","size":1.0},{"source":"28","target":"10","id":"5661","attributes":{},"color":"rgb(0,2,163)","size":1.0},{"source":"32","target":"33","id":"5666","attributes":{},"color":"rgb(0,2,163)","size":1.0},{"source":"1","target":"7","id":"5591","attributes":{},"color":"rgb(0,2,163)","size":1.0},{"source":"12","target":"1","id":"5628","attributes":{},"color":"rgb(0,2,163)","size":1.0},{"source":"65","target":"38","id":"5710","attributes":{},"color":"rgb(0,2,163)","size":1.0},{"source":"47","target":"38","id":"5691","attributes":{},"color":"rgb(0,2,163)","size":1.0},{"source":"6","target":"1","id":"5605","attributes":{},"color":"rgb(0,2,163)","size":1.0},{"source":"66","target":"18","id":"5712","attributes":{},"color":"rgb(0,2,163)","size":1.0},{"source":"0","target":"16","id":"5527","attributes":{},"color":"rgb(0,2,163)","size":1.0},{"source":"0","target":"54","id":"5565","attributes":{},"color":"rgb(0,2,163)","size":1.0},{"source":"55","target":"60","id":"5704","attributes":{},"color":"rgb(0,2,163)","size":1.0},{"source":"0","target":"20","id":"5531","attributes":{},"color":"rgb(0,2,163)","size":1.0},{"source":"2","target":"16","id":"5598","attributes":{},"color":"rgb(0,2,163)","size":1.0},{"source":"34","target":"72","id":"5668","attributes":{},"color":"rgb(0,2,163)","size":1.0},{"source":"10","target":"68","id":"5613","attributes":{},"color":"rgb(0,2,163)","size":1.0},{"source":"0","target":"6","id":"5517","attributes":{},"color":"rgb(0,2,163)","size":1.0},{"source":"1","target":"8","id":"5589","attributes":{},"color":"rgb(0,2,163)","size":1.0},{"source":"0","target":"18","id":"5529","attributes":{},"color":"rgb(0,2,163)","size":1.0},{"source":"66","target":"38","id":"5713","attributes":{},"color":"rgb(0,2,163)","size":1.0},{"source":"39","target":"27","id":"5677","attributes":{},"color":"rgb(0,2,163)","size":1.0},{"source":"72","target":"39","id":"5722","attributes":{},"color":"rgb(0,2,163)","size":1.0},{"source":"39","target":"10","id":"5679","attributes":{},"color":"rgb(0,2,163)","size":1.0},{"source":"8","target":"1","id":"5608","attributes":{},"color":"rgb(0,2,163)","size":1.0},{"source":"0","target":"31","id":"5542","attributes":{},"color":"rgb(0,2,163)","size":1.0},{"source":"18","target":"2","id":"5642","attributes":{},"color":"rgb(0,2,163)","size":1.0},{"source":"41","target":"0","id":"5682","attributes":{},"color":"rgb(0,2,163)","size":1.0},{"source":"3","target":"18","id":"5599","attributes":{},"color":"rgb(0,2,163)","size":1.0},{"source":"12","target":"10","id":"5626","attributes":{},"color":"rgb(0,2,163)","size":1.0},{"source":"0","target":"68","id":"5579","attributes":{},"color":"rgb(0,2,163)","size":1.0},{"source":"0","target":"8","id":"5519","attributes":{},"color":"rgb(0,2,163)","size":1.0},{"source":"6","target":"7","id":"5604","attributes":{},"color":"rgb(0,2,163)","size":1.0},{"source":"4","target":"28","id":"5603","attributes":{},"color":"rgb(0,2,163)","size":1.0},{"source":"49","target":"38","id":"5694","attributes":{},"color":"rgb(0,2,163)","size":1.0},{"source":"28","target":"39","id":"5662","attributes":{},"color":"rgb(0,2,163)","size":1.0},{"source":"0","target":"52","id":"5563","attributes":{},"color":"rgb(0,2,163)","size":1.0},{"source":"18","target":"7","id":"5638","attributes":{},"color":"rgb(0,2,163)","size":1.0},{"source":"0","target":"56","id":"5567","attributes":{},"color":"rgb(0,2,163)","size":1.0},{"source":"46","target":"18","id":"5689","attributes":{},"color":"rgb(0,2,163)","size":1.0},{"source":"72","target":"0","id":"5721","attributes":{},"color":"rgb(0,2,163)","size":1.0},{"source":"0","target":"62","id":"5573","attributes":{},"color":"rgb(0,2,163)","size":1.0},{"source":"7","target":"8","id":"5607","attributes":{},"color":"rgb(0,2,163)","size":1.0},{"source":"0","target":"26","id":"5537","attributes":{},"color":"rgb(0,2,163)","size":1.0},{"source":"39","target":"12","id":"5680","attributes":{},"color":"rgb(0,2,163)","size":1.0},{"source":"27","target":"17","id":"5655","attributes":{},"color":"rgb(0,2,163)","size":1.0},{"source":"28","target":"18","id":"5660","attributes":{},"color":"rgb(0,2,163)","size":1.0},{"source":"65","target":"66","id":"5711","attributes":{},"color":"rgb(0,2,163)","size":1.0},{"source":"27","target":"63","id":"5650","attributes":{},"color":"rgb(0,2,163)","size":1.0},{"source":"1","target":"12","id":"5588","attributes":{},"color":"rgb(0,2,163)","size":1.0},{"source":"53","target":"54","id":"5697","attributes":{},"color":"rgb(0,2,163)","size":1.0},{"source":"0","target":"25","id":"5536","attributes":{},"color":"rgb(0,2,163)","size":1.0},{"source":"12","target":"27","id":"5625","attributes":{},"color":"rgb(0,2,163)","size":1.0}]}